Drapion-0.1.0.dev0.dist-info/METADATA
Drapion-0.1.0.dev0.dist-info/RECORD
Drapion-0.1.0.dev0.dist-info/WHEEL
Drapion-0.1.0.dev0.dist-info/top_level.txt
drapion/__init__.py
drapion/objects.py
drapion/wrappers.py
