Metadata-Version: 2.1
Name: Drapion
Version: 0.1.0.dev0
Summary: A Simple library to facilitate consuming web API's
Home-page: https://github.com/giancarlopro/drapion
Author: Giancarlo Rocha
Author-email: giancarlorochapro@gmail.com
License: Apache 2.0
Platform: UNKNOWN
Requires-Python: >=3.5
Requires-Dist: requests (>=2.9.1)
